{
  "levels": [
    {
      "id": 1,
      "name": "Trojuholník",
      "difficulty": "Easy",
      "targetShape": {
        "width": 500,
        "height": 500,
        "pieces": [
          {
            "id": "large-triangle-1",
            "type": "large-triangle",
            "position": {
              "x": 140,
              "y": 218
            },
            "rotation": 45,
            "color": "#E57373"
          },
          {
            "id": "large-triangle-2",
            "type": "large-triangle",
            "position": {
              "x": 352.132,
              "y": 218
            },
            "rotation": 45,
            "color": "#64B5F6"
          },
          {
            "id": "medium-triangle",
            "type": "medium-triangle",
            "position": {
              "x": 246.066,
              "y": 218
            },
            "rotation": 90,
            "color": "#81C784"
          },
          {
            "id": "small-triangle-1",
            "type": "small-triangle",
            "position": {
              "x": 193.033,
              "y": 164.967
            },
            "rotation": 45,
            "color": "#FFD54F"
          },
          {
            "id": "small-triangle-2",
            "type": "small-triangle",
            "position": {
              "x": 352.132,
              "y": 218
            },
            "rotation": 135,
            "color": "#FF8A65"
          },
          {
            "id": "square",
            "type": "square",
            "position": {
              "x": 246.066,
              "y": 111.934
            },
            "rotation": 45,
            "color": "#BA68C8"
          },
          {
            "id": "parallelogram",
            "type": "parallelogram",
            "position": {
              "x": 299.099,
              "y": 164.967
            },
            "rotation": 90,
            "color": "#4DB6AC"
          }
        ]
      }
    }
  ]
}


